DynamicRoutingTask/DynamicRouting1.py
DynamicRoutingTask/DynamicRouting1_postSessionAnalysis.py
DynamicRoutingTask/OptoTagging.py
DynamicRoutingTask/RFMapping.py
DynamicRoutingTask/TaskControl.py
DynamicRoutingTask/TaskUtils.py
DynamicRoutingTask/camstimControl.py
DynamicRoutingTask/runTask.py
DynamicRoutingTask/startTask.py
DynamicRoutingTask/Analysis/DynamicRoutingAnalysisUtils.py
DynamicRoutingTask/Analysis/RLmodel.py
DynamicRoutingTask/Analysis/RLmodelHPC.py
DynamicRoutingTask/Analysis/RLmodelSlurm.py
DynamicRoutingTask/Analysis/RLmodel_old.py
DynamicRoutingTask/Analysis/RNNmodel.py
DynamicRoutingTask/Analysis/RNNmodelHPC.py
DynamicRoutingTask/Analysis/RNNmodelSlurm.py
DynamicRoutingTask/Analysis/SNc_VTA_anlaysis.py
DynamicRoutingTask/Analysis/alignBehavVideo.py
DynamicRoutingTask/Analysis/behaviorClustering.py
DynamicRoutingTask/Analysis/decoder_analysis.py
DynamicRoutingTask/Analysis/disrnn.py
DynamicRoutingTask/Analysis/dr_analysis_sam.py
DynamicRoutingTask/Analysis/dr_behav_figs.py
DynamicRoutingTask/Analysis/dr_behav_figs_old.py
DynamicRoutingTask/Analysis/dr_ephys_analysis.py
DynamicRoutingTask/Analysis/findBehaviorVideos.py
DynamicRoutingTask/Analysis/glm_hmm_sam.py
DynamicRoutingTask/Analysis/modifyTrainingSummary.py
DynamicRoutingTask/Analysis/muscimol_analysis.py
DynamicRoutingTask/Analysis/ncb_meeting_01272023.py
DynamicRoutingTask/Analysis/npc_analysis.py
DynamicRoutingTask/Analysis/npc_analysis_2.py
DynamicRoutingTask/Analysis/npc_ephys_analysis.py
DynamicRoutingTask/Analysis/opto_analysis.py
DynamicRoutingTask/Analysis/opto_ephys_analysis.py
DynamicRoutingTask/Analysis/presentation_June2023.py
DynamicRoutingTask/Analysis/regressionModel.py
DynamicRoutingTask/Analysis/sac_may2023.py
DynamicRoutingTask/Analysis/sessionSummaryFigs.py
DynamicRoutingTask/Analysis/sound_ephys_analysis.py
DynamicRoutingTask/Analysis/sound_sync_test.py
DynamicRoutingTask/Analysis/variableBlockDur.py
DynamicRoutingTask/OptoGui/OptoGui.py
dynamicroutingtask-0.1.134.dist-info/METADATA
dynamicroutingtask-0.1.134.dist-info/WHEEL
dynamicroutingtask-0.1.134.dist-info/top_level.txt
dynamicroutingtask-0.1.134.dist-info/RECORD
