Metadata-Version: 2.4
Name: DynamicRoutingTask
Version: 0.1.134
Author-email: samgale <samg@alleninstitute.org>
License: MIT
Requires-Python: >=3.9
Requires-Dist: h5py
Requires-Dist: numpy
Requires-Dist: pandas
Requires-Dist: scipy
Requires-Dist: matplotlib
